sdcat/__init__.py
sdcat/__main__.py
sdcat/cluster/__init__.py
sdcat/cluster/cluster.py
sdcat/cluster/commands.py
sdcat/cluster/embedding.py
sdcat/cluster/utils.py
sdcat/common_args.py
sdcat/config/config.ini
sdcat/config/config.py
sdcat/detect/__init__.py
sdcat/detect/commands.py
sdcat/detect/filter_util.py
sdcat/detect/model_util.py
sdcat/detect/sahi_detector.py
sdcat/detect/saliency.py
sdcat/detect/saliency_detector.py
sdcat/logger/__init__.py
sdcat/reflectance/__init__.py
sdcat/reflectance/cleaner.py
sdcat/reflectance/specularity.py
sdcat-1.27.11.dist-info/METADATA
sdcat-1.27.11.dist-info/WHEEL
sdcat-1.27.11.dist-info/entry_points.txt
sdcat-1.27.11.dist-info/RECORD
