Metadata-Version: 2.4
Name: sdcat
Version: 1.27.11
Summary: Sliced Detection and Clustering Analysis Toolkit - Developed by MBARI
License: Apache
Author: Danelle Cline
Author-email: dcline@mbari.org
Requires-Python: >=3.9,<3.12
Classifier: License :: Other/Proprietary License
Classifier: Programming Language :: Python :: 3
Classifier: Programming Language :: Python :: 3.9
Classifier: Programming Language :: Python :: 3.10
Classifier: Programming Language :: Python :: 3.11
Provides-Extra: display
Provides-Extra: rapids
Requires-Dist: cleanvision (>=0.3.6,<0.4.0)
Requires-Dist: click (>=8.1.7)
Requires-Dist: ephem (>=4.1.6,<5.0.0)
Requires-Dist: hdbscan (==0.8.37)
Requires-Dist: huggingface-hub (==0.24.0)
Requires-Dist: matplotlib (>=3.7.0)
Requires-Dist: modin[all] (>=0.32.0,<0.33.0)
Requires-Dist: numpy (>=1.22)
Requires-Dist: opencv-contrib-python-headless (==4.10.0.84)
Requires-Dist: opencv-python-headless (==4.10.0.84)
Requires-Dist: pandas (>=2.2)
Requires-Dist: pillow (==10.4.0)
Requires-Dist: pyephem (==9.99)
Requires-Dist: pytz (>=2024.1,<2025.0)
Requires-Dist: sahi (>=0.11.20,<0.12.0)
Requires-Dist: scikit-image (>=0.24.0,<0.25.0)
Requires-Dist: scikit-learn (==1.4.0rc1)
Requires-Dist: seaborn (>=0.13.2)
Requires-Dist: torch (>=2.3.1,<3.0.0)
Requires-Dist: torchvision (==0.18.1)
Requires-Dist: tqdm (>=4.66.4)
Requires-Dist: transformers (>=4.42.4,<5.0.0)
Requires-Dist: umap-learn (>=0.5.5)
